[
    {
        "hosts": "微软/清华大学/中国工程院",
        "link": "https://biendata.com/competition/scholar/winners/",
        "ddl": "20171009",
        "type": "画像/分类/预测",
        "pic": "https://github.com/geekinglcq/CDCS/blob/master/img/OPEDAC.jpg?raw=true",
        "platform": "biendata",
        "solutions": [
            {
                "id": 1,
                "rank": 1
            },
            {
                "id": 2,
                "rank": 2
            },
            {
                "id": 3,
                "rank": 3
            }
        ],
        "name": "2017 开放学术精准画像大赛"
    },
    {
        "hosts": "中国人工智能学会/摩拜",
        "link": "https://biendata.com/competition/mobike/",
        "ddl": "20170925",
        "type": "预测",
        "pic": "https://github.com/geekinglcq/CDCS/blob/master/img/mobike.jpg?raw=true",
        "platform": "biendata",
        "solutions": [
            {
                "id": 4,
                "rank": 1
            },
            {
                "id": 5,
                "rank": 2
            },
            {
                "id": 6,
                "rank": 3
            }
        ],
        "name": "2017 摩拜杯算法挑战赛"
    },
    {
        "hosts": "SMP/CSDN",
        "link": "https://biendata.com/competition/smpcup2017/",
        "ddl": "20170811",
        "type": "画像",
        "pic": "https://github.com/geekinglcq/CDCS/blob/master/img/SMP_CUP_2017.png?raw=true",
        "platform": "biendata",
        "solutions": [
            {
                "id": 8,
                "rank": "6"
            }
        ],
        "name": "SMP CUP CSDN用户画像 2017"
    },
    {
        "hosts": "中国人工智能协会/知乎",
        "link": "https://biendata.com/competition/zhihu/",
        "ddl": "20170815",
        "type": "分类/标签",
        "pic": "https://github.com/geekinglcq/CDCS/blob/master/img/zhihu17.jpg?raw=true",
        "platform": "biendata",
        "solutions": [
            {
                "id": 9,
                "rank": "1"
            },
            {
                "id": 10,
                "rank": "2"
            },
            {
                "id": 11,
                "rank": "3"
            }
        ],
        "name": "2017 知乎看山杯机器学习挑战赛"
    },
    {
        "hosts": "今日头条/中国人工智能协会",
        "link": "https://biendata.com/competition/bytecup2016/winners/",
        "ddl": "20161120",
        "type": "预测",
        "pic": "https://github.com/geekinglcq/CDCS/blob/master/img/byte16.png?raw=true",
        "platform": "biendata",
        "solutions": [
            {
                "id": 12,
                "rank": "2"
            }
        ],
        "name": "2016 Byte Cup国际机器学习竞赛"
    },
    {
        "hosts": "SMP/新浪微博",
        "link": "https://biendata.com/competition/smpcup2016/",
        "ddl": "20160921",
        "type": "画像/分类",
        "pic": "https://github.com/geekinglcq/CDCS/blob/master/img/SMP_CUP_2016.png?raw=true",
        "platform": "biendata",
        "solutions": [
            {
                "id": 13,
                "rank": "2"
            },
            {
                "id": 14,
                "rank": "5"
            }
        ],
        "name": "SMP CUP 2016"
    },
    {
        "hosts": "蚂蚁金服/CCF",
        "link": "https://tianchi.aliyun.com/competition/introduction.htm?spm=5176.100066.333.6.XHo01D&raceId=231587",
        "ddl": "20161216",
        "type": "预测",
        "pic": "https://github.com/geekinglcq/CDCS/blob/master/img/tianchi.png?raw=true",
        "platform": "tianchi",
        "solutions": [
            {
                "id": 15,
                "rank": "1"
            }
        ],
        "name": "2016 CCF大数据与计算智能大赛——O2O优惠券使用预测"
    },
    {
        "hosts": "阿里音乐",
        "link": "https://tianchi.aliyun.com/competition/introduction.htm?raceId=231531",
        "ddl": "20160715",
        "type": "预测",
        "pic": "https://github.com/geekinglcq/CDCS/blob/master/img/ali_music.jpg?raw=true",
        "platform": "tianchi",
        "solutions": [
            {
                "id": 16,
                "rank": "6"
            }
        ],
        "name": "阿里音乐流行趋势预测大赛"
    },
    {
        "hosts": "菜鸟网络",
        "link": "https://tianchi.aliyun.com/competition/information.htm?spm=0.0.0.0.sUOLE8&raceId=231530&_lang=zh_CN",
        "ddl": "20160615",
        "type": "预测",
        "pic": "https://github.com/geekinglcq/CDCS/blob/master/img/cainiao.jpg?raw=true",
        "platform": "tianchi",
        "solutions": [
            {
                "id": 17,
                "rank": "6"
            },
            {
                "id": 18,
                "rank": "10"
            }
        ],
        "name": "菜鸟-需求预测与分仓规划"
    },
    {
        "hosts": "广东省人民政府",
        "link": "https://tianchi.aliyun.com/competition/introduction.htm?raceId=231615&_lang=en_US",
        "ddl": "20171121",
        "type": "分类",
        "pic": "https://github.com/geekinglcq/CDCS/blob/master/img/guangdong.jpg?raw=true",
        "platform": "tianchi",
        "solutions": [
            {
                "id": 19,
                "rank": "1"
            },
            {
                "id": 20,
                "rank": "2"
            },
            {
                "id": 21,
                "rank": "3"
            }
        ],
        "name": "广东政务数据创新大赛—智能算法赛"
    },
    {
        "hosts": "中国地震局/阿里云",
        "link": "https://tianchi.aliyun.com/competition/information.htm?raceId=231606",
        "ddl": "20170927",
        "type": "预测/分类",
        "pic": "https://github.com/geekinglcq/CDCS/blob/master/img/earthquake.jpg?raw=true",
        "platform": "tianchi",
        "solutions": [
            {
                "id": 22,
                "rank": "2"
            }
        ],
        "name": "余震捕捉AI大赛"
    },
    {
        "hosts": "阿里云/intel/零氪科技",
        "link": "https://tianchi.aliyun.com/competition/introduction.htm?raceId=231601",
        "ddl": "20170926",
        "type": "预测",
        "pic": "https://github.com/geekinglcq/CDCS/blob/master/img/medAI_1.jpg?raw=true",
        "platform": "tianchi",
        "solutions": [
            {
                "id": 23,
                "rank": "1"
            },
            {
                "id": 24,
                "rank": "2"
            },
            {
                "id": 25,
                "rank": "3"
            }
        ],
        "name": "天池医疗AI大赛[第一季]：肺部结节智能诊断"
    },
    {
        "hosts": "中国社会保险学会/阿里云/数梦工场",
        "link": "https://tianchi.aliyun.com/competition/introduction.htm?raceId=231607",
        "ddl": "20170918",
        "type": "分类/开放",
        "pic": "https://github.com/geekinglcq/CDCS/blob/master/img/ensure.jpg?raw=true",
        "platform": "tianchi",
        "solutions": [
            {
                "id": 26,
                "rank": "2"
            },
            {
                "id": 27,
                "rank": "3"
            },
            {
                "id": 28,
                "rank": "4"
            }
        ],
        "name": "全国社会保险大数据应用创新大赛"
    },
    {
        "hosts": "贵州省大数据发展管理局/贵州省交通运输局",
        "link": "https://tianchi.aliyun.com/competition/introduction.htm?raceId=231598",
        "ddl": "20170915",
        "type": "预测",
        "pic": "https://github.com/geekinglcq/CDCS/blob/master/img/guizhou_jiaotong.jpg?raw=true",
        "platform": "tianchi",
        "solutions": [
            {
                "id": 29,
                "rank": "1"
            },
            {
                "id": 30,
                "rank": "2"
            },
            {
                "id": 31,
                "rank": "3"
            }
        ],
        "name": "智慧交通预测挑战赛"
    },
    {
        "hosts": "厦门航空/阿里云",
        "link": "https://tianchi.aliyun.com/competition/introduction.htm?raceId=231609",
        "ddl": "20170905",
        "type": "分类/优化",
        "pic": "https://github.com/geekinglcq/CDCS/blob/master/img/airAI.jpg?raw=true",
        "platform": "tianchi",
        "solutions": [
            {
                "id": 32,
                "rank": "2"
            },
            {
                "id": 33,
                "rank": "3"
            }
        ],
        "name": "智慧航空AI大赛"
    },
    {
        "hosts": "江苏省扬中市高新技术产业开发区/大航集团/阿里云",
        "link": "https://tianchi.aliyun.com/competition/introduction.htm?raceId=231602",
        "ddl": "20170720",
        "type": "预测",
        "pic": "https://github.com/geekinglcq/CDCS/blob/master/img/elecAI.jpg?raw=true",
        "platform": "tianchi",
        "solutions": [
            {
                "id": 34,
                "rank": "1"
            },
            {
                "id": 35,
                "rank": "2"
            },
            {
                "id": 36,
                "rank": "3"
            }
        ],
        "name": "大航杯“智造扬中”电力AI大赛"
    },
    {
        "hosts": "深圳市气象局/阿里云",
        "link": "https://tianchi.aliyun.com/competition/introduction.htm?raceId=231596",
        "ddl": "20170702",
        "type": "预测",
        "pic": "https://github.com/geekinglcq/CDCS/blob/master/img/CIKM17.jpg?raw=true",
        "platform": "tianchi",
        "solutions": [
            {
                "id": 37,
                "rank": "1"
            }
        ],
        "name": "CIKM AnalytiCup 2017"
    },
    {
        "hosts": "阿里聚安全",
        "link": "https://tianchi.aliyun.com/competition/introduction.htm?raceId=231592",
        "ddl": "20170316",
        "type": "分类",
        "pic": "https://github.com/geekinglcq/CDCS/blob/master/img/aliju.jpg?raw=true",
        "platform": "tianchi",
        "solutions": [
            {
                "id": 38,
                "rank": "37"
            }
        ],
        "name": "阿里聚安全算法挑战赛"
    },
    {
        "hosts": "阿里云/KDD",
        "link": "https://tianchi.aliyun.com/competition/introduction.htm?raceId=231597",
        "ddl": "20170601",
        "type": "预测",
        "pic": "https://github.com/geekinglcq/CDCS/blob/master/img/KDD17.jpg?raw=true",
        "platform": "tianchi",
        "solutions": [
            {
                "id": 39,
                "rank": "1"
            },
            {
                "id": 40,
                "rank": "2"
            },
            {
                "id": 41,
                "rank": "3"
            },
            {
                "id": 42,
                "rank": "4"
            }
        ],
        "name": "KDD CUP 2017"
    },
    {
        "hosts": "蚂蚁金服",
        "link": "https://tianchi.aliyun.com/competition/introduction.htm?raceId=231591",
        "ddl": "20170314",
        "type": "预测",
        "pic": "https://github.com/geekinglcq/CDCS/blob/master/img/IJCAI17.jpg?raw=true",
        "platform": "tianchi",
        "solutions": [
            {
                "id": 43,
                "rank": "1"
            },
            {
                "id": 44,
                "rank": "2"
            },
            {
                "id": 45,
                "rank": "3"
            }
        ],
        "name": "IJCAI-17 口碑商家客流量预测"
    },
    {
        "hosts": "蚂蚁金服",
        "link": "https://tianchi.aliyun.com/competition/rankingList.htm?raceId=231587",
        "ddl": "20161216",
        "type": "预测",
        "pic": "https://github.com/geekinglcq/CDCS/blob/master/img/O2Ocoupon.jpg?raw=true",
        "platform": "tianchi",
        "solutions": [
            {
                "id": 46,
                "rank": "1"
            },
            {
                "id": 47,
                "rank": "16"
            }
        ],
        "name": "生活大实惠：O2O优惠券使用预测"
    },
    {
        "hosts": "广东省人民政府",
        "link": "https://tianchi.aliyun.com/competition/introduction.htm?raceId=231588",
        "ddl": "20161128",
        "type": "预测",
        "pic": "https://github.com/geekinglcq/CDCS/blob/master/img/guangdong.jpg?raw=true",
        "platform": "tianchi",
        "solutions": [
            {
                "id": 48,
                "rank": "441"
            }
        ],
        "name": "【广东大赛】机场客流量的时空分布预测"
    },
    {
        "hosts": "新浪微博",
        "link": "https://tianchi.aliyun.com/competition/introduction.htm?raceId=5",
        "ddl": "20151105",
        "type": "预测",
        "pic": "https://github.com/geekinglcq/CDCS/blob/master/img/weibo.jpg?raw=true",
        "platform": "tianchi",
        "solutions": [
            {
                "id": 49,
                "rank": "?"
            }
        ],
        "name": "新浪微博互动预测大赛"
    },
    {
        "hosts": "阿里巴巴 广东省人民政府",
        "link": "https://tianchi.aliyun.com/competition/introduction.htm?spm=5176.100066.0.0.6acd33afYmcuAD&raceId=231682",
        "ddl": "20181106",
        "type": "CV分类",
        "platform": "tianchi",
        "solutions": [
            {
                "id": 50,
                "rank": "1"
            },
            {
                "id": 51,
                "rank": "2"
            },
            {
                "id": 52,
                "rank": "3"
            },
            {
                "id": 53,
                "rank": "4"
            },
            {
                "id": 54,
                "rank": "5"
            },
            {
                "id": 55,
                "rank": "6"
            }
        ],
        "name": "2018广东工业智造大数据创新大赛——智能算法赛 铝型材表面瑕疵识别"
    },
    {
        "hosts": "之江实验室、浙江省人工智能发展专家委员会（AI TOP 30）、中国人工智能产业发展联盟（AIIA）",
        "link": "https://tianchi.aliyun.com/competition/introduction.htm?spm=5176.100066.0.0.6acd33afYmcuAD&raceId=231677",
        "ddl": "20181030",
        "type": "CV 目标检测",
        "platform": "tianchi",
        "solutions": [
            {
                "id": 56,
                "rank": "baseline"
            }
        ],
        "name": "2018之江杯全球人工智能大赛 零样本图像目标识别"
    },
    {
        "hosts": "之江实验室、浙江省人工智能发展专家委员会（AI TOP 30）、中国人工智能产业发展联盟（AIIA）",
        "link": "https://tianchi.aliyun.com/competition/introduction.htm?spm=5176.100066.0.0.6acd33afYmcuAD&raceId=231676",
        "ddl": "20181030",
        "type": "视频识别 问答",
        "platform": "tianchi",
        "solutions": [
            {
                "id": 57,
                "rank": "?"
            }
        ],
        "name": "2018之江杯全球人工智能大赛 ：视频识别&问答"
    },
    {
        "hosts": "ICDM深圳气象局 香港天文台",
        "link": "https://tianchi.aliyun.com/competition/introduction.htm?spm=5176.100066.0.0.6acd33afP6RraT&raceId=231662",
        "ddl": "20181010",
        "type": "预测 回归",
        "platform": "tianchi",
        "solutions": [
            {
                "id": 58,
                "rank": "1"
            },
            {
                "id": 59,
                "rank": "2"
            },
            {
                "id": 60,
                "rank": "3"
            },
            {
                "id": 61,
                "rank": "4"
            },
            {
                "id": 62,
                "rank": "5"
            }
        ],
        "name": "IEEE ICDM 2018 全球气象AI挑战赛"
    },
    {
        "hosts": "阿里巴巴",
        "link": "https://tianchi.aliyun.com/competition/introduction.htm?spm=5176.11165320.5678.1.205d3d78uOUSPA&raceId=231669",
        "ddl": "20180921",
        "type": "预测",
        "platform": "tianchi",
        "solutions": [
            {
                "id": 63,
                "rank": "1"
            },
            {
                "id": 64,
                "rank": "2"
            },
            {
                "id": 65,
                "rank": "3"
            },
            {
                "id": 66,
                "rank": "4"
            }
        ],
        "name": "天池云上智能降雨量预测"
    },
    {
        "hosts": "江苏省无锡经济开发区 阿里云",
        "link": "https://tianchi.aliyun.com/competition/introduction.htm?spm=5176.100066.0.0.6acd33afP6RraT&raceId=231666",
        "ddl": "20180913",
        "type": "CV",
        "platform": "tianchi",
        "solutions": [
            {
                "id": 67,
                "rank": "14"
            }
        ],
        "name": "雪浪制造AI挑战赛—视觉计算辅助良品检测"
    },
    {
        "hosts": "阿里巴巴",
        "link": "https://tianchi.aliyun.com/competition/introduction.htm?spm=5176.100066.0.0.6acd33afP6RraT&raceId=231663",
        "ddl": "20180907",
        "type": "调度 优化",
        "platform": "tianchi",
        "solutions": [
            {
                "id": 68,
                "rank": "18"
            }
        ],
        "name": "阿里巴巴全球调度算法大赛"
    },
    {
        "hosts": "中国证券投资基金业协会、华夏基金、易方达、通联数据、阿里云",
        "link": "https://tianchi.aliyun.com/competition/introduction.htm?spm=5176.100066.0.0.6acd33afP6RraT&raceId=231660",
        "ddl": "20180824",
        "type": "预测",
        "platform": "tianchi",
        "solutions": [
            {
                "id": 69,
                "rank": "1"
            },
            {
                "id": 70,
                "rank": "2"
            },
            {
                "id": 71,
                "rank": "3"
            },
            {
                "id": 72,
                "rank": "4"
            },
            {
                "rank": "答辩视频",
                "id": 76
            },
            {
                "rank": "30",
                "id": 77
            },
            {
                "rank": "?",
                "id": 78
            }
        ],
        "name": "FDDC2018金融算法挑战赛01－A股上市公司季度营收预测"
    },
    {
        "hosts": "中国证券投资基金业协会、华夏基金、易方达、通联数据、阿里云",
        "link": "https://tianchi.aliyun.com/competition/introduction.htm?spm=5176.100066.0.0.6acd33afP6RraT&raceId=231659",
        "ddl": "20180824",
        "type": "NLP 信息抽取",
        "platform": "tianchi",
        "solutions": [
            {
                "id": 73,
                "rank": "1"
            },
            {
                "id": 74,
                "rank": "3"
            },
            {
                "id": 75,
                "rank": "4"
            }
        ],
        "name": "FDDC2018金融算法挑战赛02－A股上市公司公告信息抽取"
    },
    {
        "name": "Byte Cup 2018 国际机器学习竞赛",
        "link": "https://biendata.com/forum/index_category/33",
        "type": "文本生成/摘要/NLP",
        "platform": "biendata",
        "hosts": "字节跳动",
        "ddl": "20181206",
        "solutions": [
            {
                "rank": "6",
                "id": 79
            },
            {
                "rank": "23",
                "id": 80
            }
        ]
    },
    {
        "name": "2018开放学术数据挖掘大赛",
        "link": "https://www.biendata.com/competition/scholar2018/",
        "type": "聚类",
        "platform": "biendata",
        "hosts": "AMiner.org",
        "ddl": "20181201",
        "solutions": [
            {
                "rank": "4",
                "id": 81
            }
        ]
    },
    {
        "name": "OGeek算法挑战赛",
        "link": "",
        "type": "预测",
        "platform": "tianchi",
        "hosts": "OPPO",
        "ddl": "20181203",
        "solutions": [
            {
                "rank": "9",
                "id": 82
            },
            {
                "rank": "7",
                "id": 83
            },
            {
                "rank": "2",
                "id": 84
            },
            {
                "rank": "3",
                "id": 85
            },
            {
                "rank": "6",
                "id": 86
            },
            {
                "rank": "10+",
                "id": 87
            }
        ]
    },
    {
        "name": "瑞金医院MMC人工智能辅助构建知识图谱大赛",
        "link": "https://tianchi.aliyun.com/competition/entrance/231687/introduction",
        "type": "知识图谱",
        "platform": "tianchi",
        "hosts": "阿里/瑞金医院",
        "ddl": "20181206",
        "solutions": [
            {
                "rank": "1",
                "id": 88
            },
            {
                "rank": "2",
                "id": 89
            },
            {
                "rank": "4",
                "id": 90
            },
            {
                "rank": "5",
                "id": 91
            }
        ]
    },
    {
        "name": "津南数字制造算法挑战赛——赛场一：原料企业工艺优化",
        "link": "https://tianchi.aliyun.com/competition/entrance/231695/introduction?spm=5176.12281957.1004.16.38b076d8d9Bkba",
        "type": "预测、医药化学",
        "platform": "tianchi",
        "hosts": "津南区政府 阿里云",
        "ddl": "20190221",
        "solutions": [
            {
                "rank": "？",
                "id": 92
            },
            {
                "rank": "6",
                "id": 93
            },
            {
                "rank": "17",
                "id": 94
            }
        ]
    },
    {
        "name": "2018云从人头计数",
        "link": "https://www.biendata.com/competition/cloudcup2018/",
        "type": "CV",
        "platform": "biendata",
        "hosts": "云从科技",
        "ddl": "20190129",
        "solutions": [
            {
                "rank": "1",
                "id": 95
            }
        ]
    },
    {
        "name": "2018年甜橙金融杯大数据建模大赛",
        "link": "http://www.dcjingsai.com/common/cmpt/2018%E5%B9%B4%E7%94%9C%E6%A9%99%E9%87%91%E8%9E%8D%E6%9D%AF%E5%A4%A7%E6%95%B0%E6%8D%AE%E5%BB%BA%E6%A8%A1%E5%A4%A7%E8%B5%9B_%E7%AB%9E%E8%B5%9B%E4%BF%A1%E6%81%AF.html",
        "type": "分类、金融",
        "platform": "DC",
        "hosts": "甜橙金融",
        "ddl": "20181228",
        "solutions": [
            {
                "rank": "6",
                "id": 96
            },
            {
                "rank": "9",
                "id": 97
            }
        ]
    },
    {
        "name": "国能日新光伏功率预测大赛",
        "link": "http://www.dcjingsai.com/common/cmpt/%E5%9B%BD%E8%83%BD%E6%97%A5%E6%96%B0%E5%85%89%E4%BC%8F%E5%8A%9F%E7%8E%87%E9%A2%84%E6%B5%8B%E5%A4%A7%E8%B5%9B_%E7%AB%9E%E8%B5%9B%E4%BF%A1%E6%81%AF.html",
        "type": "预测",
        "platform": "DC",
        "hosts": "国能日新",
        "ddl": "20181203",
        "solutions": [
            {
                "rank": "21",
                "id": 98
            },
            {
                "rank": "?",
                "id": 99
            }
        ]
    },
    {
        "name": "第3届 融360天机智能金融算法挑战赛",
        "link": "http://www.dcjingsai.com/common/cmpt/%E7%AC%AC3%E5%B1%8A%20%E8%9E%8D360%E5%A4%A9%E6%9C%BA%E6%99%BA%E8%83%BD%E9%87%91%E8%9E%8D%E7%AE%97%E6%B3%95%E6%8C%91%E6%88%98%E8%B5%9B_%E7%AB%9E%E8%B5%9B%E4%BF%A1%E6%81%AF.html",
        "type": "金融",
        "platform": "DC",
        "hosts": "融360",
        "ddl": "20181110",
        "solutions": [
            {
                "rank": "6",
                "id": 100
            },
            {
                "rank": "5",
                "id": 101
            },
            {
                "rank": "?",
                "id": 102
            }
        ]
    }
]